interrogate/__init__.py
interrogate/__main__.py
interrogate/badge_gen.py
interrogate/cli.py
interrogate/config.py
interrogate/coverage.py
interrogate/utils.py
interrogate/visit.py
interrogate/badge/flat-square-modified-style.svg
interrogate/badge/flat-square-style.svg
interrogate/badge/flat-style.svg
interrogate/badge/for-the-badge-style.svg
interrogate/badge/plastic-style.svg
interrogate/badge/social-style.svg
interrogate-1.7.0.dist-info/LICENSE
interrogate-1.7.0.dist-info/METADATA
interrogate-1.7.0.dist-info/WHEEL
interrogate-1.7.0.dist-info/entry_points.txt
interrogate-1.7.0.dist-info/top_level.txt
interrogate-1.7.0.dist-info/RECORD
