Metadata-Version: 2.1
Name: interrogate
Version: 1.7.0
Summary: Interrogate a codebase for docstring coverage.
Home-page: https://interrogate.readthedocs.io
Author: Lynn Root
Author-email: lynn@lynnroot.com
Maintainer: Lynn Root
Maintainer-email: lynn@lynnroot.com
Project-URL: Documentation, https://interrogate.readthedocs.io
Project-URL: Bug Tracker, https://github.com/econchick/interrogate/issues
Project-URL: Source Code, https://github.com/econchick/interrogate
Keywords: documentation,coverage,quality
Classifier: Development Status :: 5 - Production/Stable
Classifier: Intended Audience :: Developers
Classifier: Natural Language :: English
Classifier: License :: OSI Approved :: MIT License
Classifier: Operating System :: OS Independent
Classifier: Programming Language :: Python :: 3.8
Classifier: Programming Language :: Python :: 3.9
Classifier: Programming Language :: Python :: 3.10
Classifier: Programming Language :: Python :: 3.11
Classifier: Programming Language :: Python :: 3.12
Classifier: Topic :: Software Development :: Documentation
Classifier: Topic :: Software Development :: Libraries :: Python Modules
Classifier: Topic :: Software Development :: Quality Assurance
Requires-Python: >=3.8
License-File: LICENSE
Requires-Dist: attrs
Requires-Dist: click>=7.1
Requires-Dist: colorama
Requires-Dist: py
Requires-Dist: tabulate
Requires-Dist: tomli; python_version < "3.11"
Provides-Extra: png
Requires-Dist: cairosvg; extra == "png"
Provides-Extra: docs
Requires-Dist: sphinx; extra == "docs"
Requires-Dist: sphinx-autobuild; extra == "docs"
Provides-Extra: tests
Requires-Dist: pytest; extra == "tests"
Requires-Dist: pytest-cov; extra == "tests"
Requires-Dist: pytest-mock; extra == "tests"
Requires-Dist: coverage[toml]; extra == "tests"
Provides-Extra: dev
Requires-Dist: cairosvg; extra == "dev"
Requires-Dist: sphinx; extra == "dev"
Requires-Dist: sphinx-autobuild; extra == "dev"
Requires-Dist: pytest; extra == "dev"
Requires-Dist: pytest-cov; extra == "dev"
Requires-Dist: pytest-mock; extra == "dev"
Requires-Dist: coverage[toml]; extra == "dev"
Requires-Dist: wheel; extra == "dev"
Requires-Dist: pre-commit; extra == "dev"
